zut/__init__.py
zut/__main__.py
zut/_version.py
zut/api.py
zut/callback.py
zut/choices.py
zut/commands.py
zut/config.py
zut/console.py
zut/convert.py
zut/csv.py
zut/encoding.py
zut/env.py
zut/errors.py
zut/excel.py
zut/gpg.py
zut/graph.py
zut/json.py
zut/locale.py
zut/logging.py
zut/net.py
zut/numbers.py
zut/paths.py
zut/perf.py
zut/process.py
zut/secrets.py
zut/slugs.py
zut/sql.py
zut/tables.py
zut/time.py
zut/types.py
zut/unittest.py
zut/urls.py
zut/db/__init__.py
zut/db/mariadb.py
zut/db/mysql.py
zut/db/pg.py
zut/db/sqlite.py
zut/db/sqlserver.py
zut/db/sqlutils/postgresql.sql
zut-4.0.5.dist-info/licenses/LICENSE.txt
zut-4.0.5.dist-info/METADATA
zut-4.0.5.dist-info/WHEEL
zut-4.0.5.dist-info/entry_points.txt
zut-4.0.5.dist-info/top_level.txt
zut-4.0.5.dist-info/RECORD
