Metadata-Version: 2.4
Name: zut
Version: 4.0.5
Summary: Reusable Python utilities to avoid reinventing the wheel.
Author-email: Sébastien Hocquet <seb@ipamo.net>
Project-URL: Homepage, https://codeberg.org/ipamo/zut
Project-URL: Bug Tracker, https://codeberg.org/ipamo/zut/issues
Keywords: reusable,util,utils,wheel,common,commons,base,csv,excel,db,database,load,bulk,insert,sqlite,postgresql,pg,mysql,maria,mariadb,sqlserver,mssql
Classifier: Development Status :: 5 - Production/Stable
Classifier: License :: OSI Approved :: MIT License
Classifier: Operating System :: OS Independent
Classifier: Programming Language :: Python :: 3
Classifier: Topic :: Software Development :: Libraries
Requires-Python: >=3.7
License-File: LICENSE.txt
Provides-Extra: pg
Requires-Dist: psycopg[binary]; extra == "pg"
Requires-Dist: sqlparse; extra == "pg"
Requires-Dist: tzlocal; (python_version < "3.9" or sys_platform == "win32") and extra == "pg"
Requires-Dist: pytz; python_version < "3.9" and extra == "pg"
Requires-Dist: tzdata; (python_version >= "3.9" and sys_platform == "win32") and extra == "pg"
Provides-Extra: postgresql
Requires-Dist: psycopg[binary]; extra == "postgresql"
Requires-Dist: sqlparse; extra == "postgresql"
Requires-Dist: tzlocal; (python_version < "3.9" or sys_platform == "win32") and extra == "postgresql"
Requires-Dist: pytz; python_version < "3.9" and extra == "postgresql"
Requires-Dist: tzdata; (python_version >= "3.9" and sys_platform == "win32") and extra == "postgresql"
Provides-Extra: mysql
Requires-Dist: mysqlclient; extra == "mysql"
Requires-Dist: sqlparse; extra == "mysql"
Requires-Dist: tzlocal; (python_version < "3.9" or sys_platform == "win32") and extra == "mysql"
Requires-Dist: pytz; python_version < "3.9" and extra == "mysql"
Requires-Dist: tzdata; (python_version >= "3.9" and sys_platform == "win32") and extra == "mysql"
Provides-Extra: mariadb
Requires-Dist: mysqlclient; extra == "mariadb"
Requires-Dist: sqlparse; extra == "mariadb"
Requires-Dist: tzlocal; (python_version < "3.9" or sys_platform == "win32") and extra == "mariadb"
Requires-Dist: pytz; python_version < "3.9" and extra == "mariadb"
Requires-Dist: tzdata; (python_version >= "3.9" and sys_platform == "win32") and extra == "mariadb"
Provides-Extra: sqlserver
Requires-Dist: pyodbc; extra == "sqlserver"
Requires-Dist: sqlparams; extra == "sqlserver"
Requires-Dist: sqlparse; extra == "sqlserver"
Requires-Dist: tzlocal; (python_version < "3.9" or sys_platform == "win32") and extra == "sqlserver"
Requires-Dist: pytz; python_version < "3.9" and extra == "sqlserver"
Requires-Dist: tzdata; (python_version >= "3.9" and sys_platform == "win32") and extra == "sqlserver"
Provides-Extra: mssql
Requires-Dist: pyodbc; extra == "mssql"
Requires-Dist: sqlparams; extra == "mssql"
Requires-Dist: sqlparse; extra == "mssql"
Requires-Dist: tzlocal; (python_version < "3.9" or sys_platform == "win32") and extra == "mssql"
Requires-Dist: pytz; python_version < "3.9" and extra == "mssql"
Requires-Dist: tzdata; (python_version >= "3.9" and sys_platform == "win32") and extra == "mssql"
Provides-Extra: sqlite
Requires-Dist: sqlparse; extra == "sqlite"
Requires-Dist: tzlocal; (python_version < "3.9" or sys_platform == "win32") and extra == "sqlite"
Requires-Dist: pytz; python_version < "3.9" and extra == "sqlite"
Requires-Dist: tzdata; (python_version >= "3.9" and sys_platform == "win32") and extra == "sqlite"
Provides-Extra: tz
Requires-Dist: tzlocal; (python_version < "3.9" or sys_platform == "win32") and extra == "tz"
Requires-Dist: pytz; python_version < "3.9" and extra == "tz"
Requires-Dist: tzdata; (python_version >= "3.9" and sys_platform == "win32") and extra == "tz"
Provides-Extra: tabulate
Requires-Dist: tabulate; extra == "tabulate"
Provides-Extra: excel
Requires-Dist: openpyxl; extra == "excel"
Requires-Dist: defusedxml; extra == "excel"
Provides-Extra: perf
Requires-Dist: psutil; extra == "perf"
Provides-Extra: all
Requires-Dist: psycopg[binary]; extra == "all"
Requires-Dist: mysqlclient; extra == "all"
Requires-Dist: pyodbc; extra == "all"
Requires-Dist: sqlparams; extra == "all"
Requires-Dist: sqlparse; extra == "all"
Requires-Dist: tzlocal; (python_version < "3.9" or sys_platform == "win32") and extra == "all"
Requires-Dist: pytz; python_version < "3.9" and extra == "all"
Requires-Dist: tzdata; (python_version >= "3.9" and sys_platform == "win32") and extra == "all"
Requires-Dist: tabulate; extra == "all"
Requires-Dist: openpyxl; extra == "all"
Requires-Dist: defusedxml; extra == "all"
Requires-Dist: psutil; extra == "all"
Dynamic: license-file
